opendma/api/__init__.py
opendma/api/constants.py
opendma/api/helpers.py
opendma/api/interfaces.py
opendma_api-0.8.0.dist-info/licenses/LICENSE
opendma_api-0.8.0.dist-info/METADATA
opendma_api-0.8.0.dist-info/WHEEL
opendma_api-0.8.0.dist-info/top_level.txt
opendma_api-0.8.0.dist-info/RECORD
