Metadata-Version: 2.4
Name: opendma-api
Version: 0.8.0
Summary: Python API for OpenDMA
Author: Stefan Kopf, OpenDMA Contributors
Maintainer: Stefan Kopf
License-Expression: Apache-2.0
Project-URL: Homepage, https://opendma.org
Project-URL: Repository, https://github.com/OpenDMA/opendma-python-api.git
Classifier: Development Status :: 4 - Beta
Classifier: Intended Audience :: Developers
Classifier: Programming Language :: Python :: 3.9
Classifier: Programming Language :: Python :: 3.10
Classifier: Programming Language :: Python :: 3.11
Classifier: Programming Language :: Python :: 3.12
Classifier: Programming Language :: Python :: 3.13
Classifier: Programming Language :: Python :: 3.14
Classifier: Programming Language :: Python :: 3.15
Requires-Python: >=3.9
License-File: LICENSE
Dynamic: license-file
